metamorfo/__init__.py
metamorfo/database/__init__.py
metamorfo/database/__pycache__/__init__.cpython-312.pyc
metamorfo/database/__pycache__/__init__.cpython-39.pyc
metamorfo/database/__pycache__/mongo_database.cpython-312.pyc
metamorfo/database/__pycache__/mongo_database.cpython-39.pyc
metamorfo/database/__pycache__/postgres_database.cpython-312.pyc
metamorfo/database/__pycache__/redis_database.cpython-312.pyc
metamorfo/database/__pycache__/redis_database.cpython-39.pyc
metamorfo/database/__pycache__/trino_database.cpython-312.pyc
metamorfo/database/__pycache__/trino_database.cpython-39.pyc
metamorfo/database/mongo_database.py
metamorfo/database/postgres_database.py
metamorfo/database/redis_database.py
metamorfo/database/trino_database.py
metamorfo/utility/__init__.py
metamorfo/utility/__pycache__/__init__.cpython-312.pyc
metamorfo-0.3.3.dist-info/METADATA
metamorfo-0.3.3.dist-info/WHEEL
metamorfo-0.3.3.dist-info/RECORD
