Metadata-Version: 2.3
Name: metamorfo
Version: 0.3.3
Summary: Pacotes de funções utilitárias e classes de uso geral em aplicações
Author: Guilherme Costa
Author-email: guiijc96@gmail.com
Requires-Python: >=3.9,<4.0
Classifier: Programming Language :: Python :: 3
Classifier: Programming Language :: Python :: 3.9
Classifier: Programming Language :: Python :: 3.10
Classifier: Programming Language :: Python :: 3.11
Classifier: Programming Language :: Python :: 3.12
Classifier: Programming Language :: Python :: 3.13
Provides-Extra: database
Requires-Dist: psycopg2-binary (>=2.9.10,<3.0.0) ; extra == "database"
Requires-Dist: pymongo (>=4.6.1,<5.0.0) ; extra == "database"
Requires-Dist: redis (>=5.0.1,<6.0.0) ; extra == "database"
Requires-Dist: sqlalchemy (>=2.0.25,<3.0.0) ; extra == "database"
Requires-Dist: trino (>=0.327.0,<0.328.0) ; extra == "database"
